topsis/__init__.py
topsis/__main__.py
Topsis_Prateek_101917080-1.0.0.dist-info/METADATA
Topsis_Prateek_101917080-1.0.0.dist-info/WHEEL
Topsis_Prateek_101917080-1.0.0.dist-info/top_level.txt
Topsis_Prateek_101917080-1.0.0.dist-info/RECORD
