Metadata-Version: 2.1
Name: Topsis-Prateek-101917080
Version: 1.0.0
Summary: Assignment of Prateek Bansal
Home-page: 
Author: Prateek Bansal
Author-email: prateekbansal64@gmail.com
License: MIT
Platform: UNKNOWN
Classifier: License :: OSI Approved :: MIT License
Classifier: Programming Language :: Python :: 3.6
Classifier: Programming Language :: Python :: 3.7
Classifier: Programming Language :: Python :: 3.8
